<?xml version="1.0" encoding="utf-8"?>
<WritingSystemCollection>
  <members>
	<WritingSystem>
	  <FontName>Arial</FontName>
	  <FontSize>12</FontSize>
	  <Id>v</Id>
	</WritingSystem>

	<WritingSystem>
	  <FontName>Arial</FontName>
	  <FontSize>12</FontSize>
	  <Id>en</Id>
	  <Abbreviation>eng</Abbreviation>
	  <SortUsing>en</SortUsing>
	  <SpellCheckingId>en</SpellCheckingId>
	</WritingSystem>

	<WritingSystem>
	  <FontName>Arial</FontName>
	  <FontSize>12</FontSize>
	  <Id>fr</Id>
	  <Abbreviation>fr</Abbreviation>
	  <SortUsing>fr</SortUsing>
	  <SpellCheckingId>fr</SpellCheckingId>
	</WritingSystem>

	<WritingSystem>
	  <FontName>Arial</FontName>
	  <FontSize>12</FontSize>
	  <Id>tpi</Id>
	  <Abbreviation>tp</Abbreviation>
	  <SortUsing>en</SortUsing>
	</WritingSystem>

	<WritingSystem>
	  <FontName>Arial</FontName>
	  <FontSize>12</FontSize>
	  <Id>id</Id>
	  <Abbreviation>ind</Abbreviation>
	</WritingSystem>


	<WritingSystem>
	  <FontName>Arial</FontName>
	  <FontSize>12</FontSize>
	  <Id>th</Id>
	  <Abbreviation>th</Abbreviation>
	  <SpellCheckingId>th</SpellCheckingId>
	</WritingSystem>

	<WritingSystem>
	  <FontName>Arial</FontName>
	  <FontSize>12</FontSize>
	  <Id>pt</Id>
	  <Abbreviation>por</Abbreviation>
	  <SortUsing>pt</SortUsing>
	  <SpellCheckingId>pt</SpellCheckingId>
	</WritingSystem>

	<WritingSystem>
	  <FontName>Arial</FontName>
	  <FontSize>12</FontSize>
	  <Id>es</Id>
	  <Abbreviation>esp</Abbreviation>
	  <SortUsing>es</SortUsing>
	  <SpellCheckingId>es</SpellCheckingId>
	</WritingSystem>
  </members>
</WritingSystemCollection>